amweb-0.0.5.dist-info/licenses/LICENSE
httpkit/__init__.py
httpkit/headers.py
httpkit/request.py
httpkit/response.py
httpkit/router.py
httpkit/server.py
httpkit/status.py
amweb-0.0.5.dist-info/METADATA
amweb-0.0.5.dist-info/WHEEL
amweb-0.0.5.dist-info/top_level.txt
amweb-0.0.5.dist-info/RECORD
