Metadata-Version: 2.4
Name: amweb
Version: 0.0.5
Summary: A simple Python library to build web applications.
Author-email: Amjad <amjadchoufi@gmail.com>
Project-URL: Homepage, https://github.com/HACKER-AMJAD
Classifier: Programming Language :: Python :: 3
Classifier: License :: OSI Approved :: MIT License
Classifier: Operating System :: OS Independent
Requires-Python: >=3.8
License-File: LICENSE
Dynamic: license-file
